{
  "0": {
    "Q": "¿En qué cultura se desarrolla usted en software testing?",
    "A": [],
    "N": [],
    "T": 0
  },
  "1": {
    "Q": "¿Qué idioma o idiomas quiere que el software soporte?",
    "A": [],
    "N": [],
    "T": 0
  },
  "2": {
    "Q": "¿Qué elementos se consideran ofensivos en su cultura?",
    "A": [],
    "N": [],
    "T": 0
  },
  "3": {
    "Q": "¿La religión tiene mucho impacto en su cultura?",
    "A": [],
    "N": [],
    "T": 0
  },
  "4": {
    "Q": "¿Su sociedad va muy de la mano con las tecnologías actuales?",
    "A": [],
    "N": [],
    "T": 0
  },
  "5": {
    "Q": "¿Su empresa se adapta fácilmente a nuevas tecnologías?",
    "A": [],
    "N": [],
    "T": 0
  },
  "6": {
    "Q": "¿Cuál es la tecnología más innovadora actualmente en su sociedad?",
    "A": [],
    "N": [],
    "T": 0
  },
  "7": {
    "Q": "¿Qué idiomas o lenguas habitan en el personal?",
    "A": [],
    "N": [],
    "T": 0
  },
  "8": {
    "Q": "¿Hay una unidad de respeto entre los miembros de la empresa?",
    "A": [],
    "N": [],
    "T": 0
  },
  "9": {
    "Q": "¿Hay forma de mediar los ataques a la integridad de las personas?",
    "A": [],
    "N": [],
    "T": 0
  },
}
